objects/__init__.py
objects/courseobjects.py
uiucapi/__init__.py
uiucapi/aioquery.py
uiucapi/query.py
uiucapi-1.0.1.dist-info/DESCRIPTION.rst
uiucapi-1.0.1.dist-info/METADATA
uiucapi-1.0.1.dist-info/RECORD
uiucapi-1.0.1.dist-info/WHEEL
uiucapi-1.0.1.dist-info/metadata.json
uiucapi-1.0.1.dist-info/top_level.txt
utility/__init__.py
utility/courseobjects.py
utility/parse.py
