Metadata-Version: 2.0
Name: uiucapi
Version: 1.0.1
Summary: A simple interface to the UIUC course explorer API
Home-page: https://github.com/rohits2/UIUC-API
Author: Rohit Singh
Author-email: rohits2@illinois.edu
License: MIT
Keywords: uiuc setuptools development
Platform: UNKNOWN
Classifier: Development Status :: 5 - Production/Stable
Classifier: Intended Audience :: Developers
Classifier: Topic :: Software Development :: Build Tools
Classifier: License :: OSI Approved :: MIT License
Classifier: Programming Language :: Python :: 3.5
Provides-Extra: test
Requires-Dist: coverage; extra == 'test'
